pyfacelm/__init__.py
pyfacelm/detector.py
pyfacelm-0.1.0.dist-info/licenses/LICENSE
pyfacelm-0.1.0.dist-info/METADATA
pyfacelm-0.1.0.dist-info/WHEEL
pyfacelm-0.1.0.dist-info/top_level.txt
pyfacelm-0.1.0.dist-info/RECORD
