Metadata-Version: 2.4
Name: pyfacelm
Version: 0.1.0
Summary: Minimal-dependency Python wrapper for OpenFace CLNF facial landmark detection
Home-page: https://github.com/johnwilsoniv/pyfacelm
Author: John Wilson IV
Author-email: John Wilson IV <john@example.com>
License: MIT
Project-URL: Homepage, https://github.com/johnwilsoniv/pyfacelm
Project-URL: Documentation, https://github.com/johnwilsoniv/pyfacelm/blob/main/README.md
Project-URL: Repository, https://github.com/johnwilsoniv/pyfacelm
Project-URL: Issues, https://github.com/johnwilsoniv/pyfacelm/issues
Keywords: face,facial landmarks,openface,clnf,mtcnn,computer vision
Classifier: Development Status :: 4 - Beta
Classifier: Intended Audience :: Developers
Classifier: Intended Audience :: Science/Research
Classifier: Topic :: Scientific/Engineering :: Image Recognition
Classifier: License :: OSI Approved :: MIT License
Classifier: Programming Language :: Python :: 3
Requires-Python: >=3.7
License-File: LICENSE
Requires-Dist: numpy>=1.19.0
Provides-Extra: viz
Requires-Dist: opencv-python-headless>=4.5.0; extra == "viz"
Provides-Extra: dev
Requires-Dist: pytest>=6.0; extra == "dev"
Requires-Dist: pytest-cov>=2.10; extra == "dev"
Requires-Dist: black>=20.8b1; extra == "dev"
Requires-Dist: flake8>=3.8; extra == "dev"
Dynamic: author
Dynamic: home-page
Dynamic: license-file
Dynamic: requires-python
